xgo_blockly/__init__.py
xgo_blockly/app.py
xgo_blockly/cli.py
xgo_blockly/config.py
xgo_blockly/dist/favicon.ico
xgo_blockly/dist/index.html
xgo_blockly/dist/assets/index.45c5efc9.css
xgo_blockly/dist/assets/index.f81936b9.js
xgo_blockly/dist/assets/index.f837c243.js
xgo_blockly/dist/assets/logo.e0551a52.png
xgo_blockly/dist/media/1x1.gif
xgo_blockly/dist/media/click.mp3
xgo_blockly/dist/media/click.ogg
xgo_blockly/dist/media/click.wav
xgo_blockly/dist/media/delete-icon.svg
xgo_blockly/dist/media/delete.mp3
xgo_blockly/dist/media/delete.ogg
xgo_blockly/dist/media/delete.wav
xgo_blockly/dist/media/disconnect.mp3
xgo_blockly/dist/media/disconnect.ogg
xgo_blockly/dist/media/disconnect.wav
xgo_blockly/dist/media/dropdown-arrow.svg
xgo_blockly/dist/media/foldout-icon.svg
xgo_blockly/dist/media/handclosed.cur
xgo_blockly/dist/media/handdelete.cur
xgo_blockly/dist/media/handopen.cur
xgo_blockly/dist/media/pilcrow.png
xgo_blockly/dist/media/quote0.png
xgo_blockly/dist/media/quote1.png
xgo_blockly/dist/media/resize-handle.svg
xgo_blockly/dist/media/sprites.png
xgo_blockly/dist/media/sprites.svg
xgo_blockly/dist/static/media/luwu.png
xgo_blockly/routes/__init__.py
xgo_blockly/routes/api.py
xgo_blockly/routes/static.py
xgo_blockly/services/__init__.py
xgo_blockly/services/code_executor.py
xgo_blockly/services/edulib.py
xgo_blockly/services/xgo_status.py
xgo_blockly/services/agents/__init__.py
xgo_blockly/services/agents/xgo_agent.py
xgo_blockly/services/agents/descriptions/lite.txt
xgo_blockly/services/agents/descriptions/mini.txt
xgo_blockly/services/agents/descriptions/rider.txt
xgo_blockly/services/agents/tools/__init__.py
xgo_blockly/services/agents/tools/common.py
xgo_blockly/services/agents/tools/lite.py
xgo_blockly/services/agents/tools/mini.py
xgo_blockly/services/agents/tools/rider.py
xgo_blockly/services/xgolib/__init__.py
xgo_blockly-1.2.4.dist-info/METADATA
xgo_blockly-1.2.4.dist-info/WHEEL
xgo_blockly-1.2.4.dist-info/entry_points.txt
xgo_blockly-1.2.4.dist-info/top_level.txt
xgo_blockly-1.2.4.dist-info/RECORD
