Metadata-Version: 2.4
Name: xgo-blockly
Version: 1.2.4
Summary: XGO Blockly - 图形化编程Web服务器
Home-page: https://github.com/xgo-robotics/xgo-blockly
Author: XGO Team
Author-email: XGO Team <support@xgo.com>
License: MIT
Project-URL: Homepage, https://github.com/xgo-robotics/xgo-blockly
Project-URL: Bug Reports, https://github.com/xgo-robotics/xgo-blockly/issues
Project-URL: Source, https://github.com/xgo-robotics/xgo-blockly
Project-URL: Documentation, https://docs.xgo.com/
Keywords: xgo,robot,blockly,programming,education
Classifier: Development Status :: 4 - Beta
Classifier: Intended Audience :: Education
Classifier: Intended Audience :: Developers
Classifier: License :: OSI Approved :: MIT License
Classifier: Operating System :: OS Independent
Classifier: Programming Language :: Python :: 3
Classifier: Programming Language :: Python :: 3.7
Classifier: Programming Language :: Python :: 3.8
Classifier: Programming Language :: Python :: 3.9
Classifier: Programming Language :: Python :: 3.10
Classifier: Programming Language :: Python :: 3.11
Classifier: Topic :: Education
Classifier: Topic :: Software Development :: Libraries :: Python Modules
Classifier: Framework :: Flask
Requires-Python: >=3.7
Requires-Dist: flask>=2.2.2
Requires-Dist: flask-cors>=4.0.0
Requires-Dist: psutil>=5.9.0
Requires-Dist: pyserial>=3.5
Requires-Dist: mem0ai==0.1.118
Requires-Dist: agentscope==1.0.5
Requires-Dist: opencv-python==4.11.0.86
Requires-Dist: spidev==3.6
Requires-Dist: rpi-lgpio==0.6
Requires-Dist: packaging==23.2
Requires-Dist: requests==2.32.3
Requires-Dist: xgo-pythonlib==0.3.5
Requires-Dist: onnxruntime>=1.20.0
Requires-Dist: pyzbar==0.1.9
Dynamic: author
Dynamic: home-page
Dynamic: requires-python
